pypiyangshun/__init__.py
pypiyangshun-0.0.2.data/scripts/pypiyangshun.py
pypiyangshun-0.0.2.dist-info/LICENSE
pypiyangshun-0.0.2.dist-info/METADATA
pypiyangshun-0.0.2.dist-info/WHEEL
pypiyangshun-0.0.2.dist-info/top_level.txt
pypiyangshun-0.0.2.dist-info/RECORD
