Metadata-Version: 2.1
Name: pypiyangshun
Version: 0.0.2
Summary: pypi yangshun  Linux test
Author: yangshun
Author-email: 2095686947@qq.com
License: MIT
License-File: LICENSE
